dexvstuff/__init__.py
dexvstuff/files.py
dexvstuff/jsdomruntime.py
dexvstuff/logger.py
dexvstuff/wabt_tools.py
dexvstuff-1.0.2.dist-info/METADATA
dexvstuff-1.0.2.dist-info/WHEEL
dexvstuff-1.0.2.dist-info/top_level.txt
dexvstuff-1.0.2.dist-info/RECORD
