Metadata-Version: 2.2
Name: dexvstuff
Version: 1.0.2
Summary: Stuff i use in my projects
Author-email: Dexv <dexv@dexv.lol>
Requires-Python: >=3.7
